design.sv
// Code your design here
module synchronous_fifo #(parameter DEPTH=8, DATA_WIDTH=8) (
  input clk, rst_n,
  input w_en, r_en,
  input [DATA_WIDTH-1:0] data_in,
  output reg [DATA_WIDTH-1:0] data_out,
  output full, empty
);
  
  parameter PTR_WIDTH = $clog2(DEPTH);
  reg [PTR_WIDTH:0] w_ptr, r_ptr; 
  reg [DATA_WIDTH-1:0] fifo[DEPTH];
  reg wrap_around;
  
  // Set Default values on reset.
  always@(posedge clk) begin
    if(!rst_n) begin
      w_ptr <= 0; r_ptr <= 0;
      data_out <= 0;
    end
  end
  
  // To write data to FIFO
  always@(posedge clk) begin
    if(w_en & !full)begin
      fifo[w_ptr[PTR_WIDTH-1:0]] <= data_in;
      w_ptr <= w_ptr + 1;
    end
  end
  
  // To read data from FIFO
  always@(posedge clk) begin
    if(r_en & !empty) begin
      data_out <= fifo[r_ptr[PTR_WIDTH-1:0]];
      r_ptr <= r_ptr + 1;
    end
  end
  
  assign wrap_around = w_ptr[PTR_WIDTH] ^ r_ptr[PTR_WIDTH]; 
  
  
  assign full = wrap_around & (w_ptr[PTR_WIDTH-1:0] == r_ptr[PTR_WIDTH-1:0]);
  
  
  assign empty = (w_ptr == r_ptr);
endmodule

testbench.sv
// Code your testbench here
// or browse Examples
module sync_fifo_TB;
  reg clk, rst_n;
  reg w_en, r_en;
  reg [7:0] data_in;
  wire [7:0] data_out;
  wire full, empty;
  
  synchronous_fifo s_fifo(clk, rst_n, w_en, r_en, data_in, data_out, full, empty);
  
  always #2 clk = ~clk;
  initial begin
    clk = 0; rst_n = 0;
    w_en = 0; r_en = 0;
    #3 rst_n = 1;
    drive(20);
    drive(40);
    $finish;
  end
  
  task push();
    if(!full) begin
      w_en = 1;
      data_in = $random;
      #1 $display("Push In: w_en=%b, r_en=%b, data_in=%h",w_en, r_en,data_in);
    end
    else $display("FIFO Full!! Can not push data_in=%d", data_in);
  endtask 
  
  task pop();
    if(!empty) begin
      r_en = 1;
      #1 $display("Pop Out: w_en=%b, r_en=%b, data_out=%h",w_en, r_en,data_out);
    end
    else $display("FIFO Empty!! Can not pop data_out");
  endtask
  
  task drive(int delay);
    w_en = 0; r_en = 0;
    fork
      begin
        repeat(10) begin @(posedge clk) push(); end
        w_en = 0;
      end
      begin
        #delay;
        repeat(10) begin @(posedge clk) pop(); end
        r_en = 0;
      end
    join
  endtask
  
  initial begin 
    $dumpfile("dump.vcd"); $dumpvars;
  end
endmodule

dump.vcd
$date
	Sat Nov 30 00:15:24 2024
$end
$version
	Icarus Verilog
$end
$timescale
	1s
$end
$scope module sync_fifo_TB $end
$var wire 1 ! full $end
$var wire 1 " empty $end
$var wire 8 # data_out [7:0] $end
$var reg 1 $ clk $end
$var reg 8 % data_in [7:0] $end
$var reg 1 & r_en $end
$var reg 1 ' rst_n $end
$var reg 1 ( w_en $end
$scope module s_fifo $end
$var wire 1 $ clk $end
$var wire 8 ) data_in [7:0] $end
$var wire 1 ! full $end
$var wire 1 & r_en $end
$var wire 1 ' rst_n $end
$var wire 1 ( w_en $end
$var wire 1 * wrap_around $end
$var wire 1 " empty $end
$var parameter 32 + DATA_WIDTH $end
$var parameter 32 , DEPTH $end
$var parameter 32 - PTR_WIDTH $end
$var reg 8 . data_out [7:0] $end
$var reg 4 / r_ptr [3:0] $end
$var reg 4 0 w_ptr [3:0] $end
$upscope $end
$scope task drive $end
$var integer 32 1 delay [31:0] $end
$upscope $end
$scope task pop $end
$upscope $end
$scope task push $end
$upscope $end
$upscope $end
$enddefinitions $end
$comment Show the parameter values. $end
$dumpall
b11 -
b1000 ,
b1000 +
$end
#0
$dumpvars
b0 1
bx 0
bx /
bx .
x*
bx )
0(
0'
0&
bx %
0$
bx #
x"
x!
$end
#2
0!
0*
b0 #
b0 .
1"
b0 /
b0 0
1$
#3
b10100 1
1'
#4
0$
#6
b100100 %
b100100 )
1(
1$
#8
0$
#10
0"
b1 0
b10000001 %
b10000001 )
1$
#12
0$
#14
b10 0
b1001 %
b1001 )
1$
#16
0$
#18
b11 0
b1100011 %
b1100011 )
1$
#20
0$
#22
b100 0
b1101 %
b1101 )
1$
#24
0$
#26
b101 0
b10001101 %
b10001101 )
1&
1$
#28
0$
#30
b1 /
b100100 #
b100100 .
b110 0
b1100101 %
b1100101 )
1$
#32
0$
#34
b111 0
b10 /
b10000001 #
b10000001 .
b10010 %
b10010 )
1$
#36
0$
#38
1*
b11 /
b1001 #
b1001 .
b1000 0
b1 %
b1 )
1$
#40
0$
#42
b1001 0
b100 /
b1100011 #
b1100011 .
b1101 %
b1101 )
1$
#43
0(
#44
0$
#46
b101 /
b1101 #
b1101 .
1$
#48
0$
#50
b110 /
b10001101 #
b10001101 .
1$
#52
0$
#54
b111 /
b1100101 #
b1100101 .
1$
#56
0$
#58
0*
b1000 /
b10010 #
b10010 .
1$
#60
0$
#62
1"
b1001 /
b1 #
b1 .
1$
#63
b101000 1
0&
#64
0$
#66
b1110110 %
b1110110 )
1(
1$
#68
0$
#70
0"
b1010 0
b111101 %
b111101 )
1$
#72
0$
#74
b1011 0
b11101101 %
b11101101 )
1$
#76
0$
#78
b1100 0
b10001100 %
b10001100 )
1$
#80
0$
#82
b1101 0
b11111001 %
b11111001 )
1$
#84
0$
#86
b1110 0
b11000110 %
b11000110 )
1$
#88
0$
#90
b1111 0
b11000101 %
b11000101 )
1$
#92
0$
#94
1*
b0 0
b10101010 %
b10101010 )
1$
#96
0$
#98
1!
b1 0
b11100101 %
b11100101 )
1$
#100
0$
#102
0(
1$
#104
0$
#106
1&
1$
#108
0$
#110
0!
b1010 /
b1110110 #
b1110110 .
1$
#112
0$
#114
b1011 /
b111101 #
b111101 .
1$
#116
0$
#118
b1100 /
b11101101 #
b11101101 .
1$
#120
0$
#122
b1101 /
b10001100 #
b10001100 .
1$
#124
0$
#126
b1110 /
b11111001 #
b11111001 .
1$
#128
0$
#130
b1111 /
b11000110 #
b11000110 .
1$
#132
0$
#134
0*
b0 /
b11000101 #
b11000101 .
1$
#136
0$
#138
1"
b1 /
b10101010 #
b10101010 .
1$
#140
0$
#142
0&
1$
